notion_duplicates/__init__.py
notion_duplicates/notion_duplicates.py
notion_duplicates-0.6.0.dist-info/METADATA
notion_duplicates-0.6.0.dist-info/WHEEL
notion_duplicates-0.6.0.dist-info/entry_points.txt
notion_duplicates-0.6.0.dist-info/RECORD
