Metadata-Version: 2.1
Name: notion-duplicates
Version: 0.6.0
Summary: Detect duplicated pages in a Notion database and optionallly delete them
Author: Jerome Provensal
Author-email: jeromegit@provensal.com
Requires-Python: >=3.9,<4.0
Classifier: Programming Language :: Python :: 3
Classifier: Programming Language :: Python :: 3.9
Classifier: Programming Language :: Python :: 3.10
Classifier: Programming Language :: Python :: 3.11
Requires-Dist: notion-client (>=2.2.1,<3.0.0)
